covid/__init__.py
covid/cli.py
covid/config.py
covid/john_hopkins/__init__.py
covid/john_hopkins/covid.py
covid/john_hopkins/models.py
covid/worldometers/__init__.py
covid/worldometers/covid.py
covid/worldometers/models.py
covid-3.0.0.dist-info/LICENSE.txt
covid-3.0.0.dist-info/METADATA
covid-3.0.0.dist-info/WHEEL
covid-3.0.0.dist-info/entry_points.txt
covid-3.0.0.dist-info/RECORD
