Metadata-Version: 2.1
Name: covid
Version: 3.0.0
Summary: Python package to get information regarding the novel corona virus provided by Johns Hopkins university and worldometers.info
Home-page: https://nf1s.github.io/covid/
License: MIT
Author: nf1s
Requires-Python: >=3.10,<4.0
Classifier: License :: OSI Approved :: MIT License
Classifier: Programming Language :: Python :: 3
Classifier: Programming Language :: Python :: 3.10
Classifier: Programming Language :: Python :: 3.11
Classifier: Programming Language :: Python :: 3.12
Provides-Extra: docs
Requires-Dist: beautifulsoup4
Requires-Dist: bleach (>=3)
Requires-Dist: click
Requires-Dist: importlib-metadata
Requires-Dist: inflection
Requires-Dist: jeepney (>=0.4.2)
Requires-Dist: mkdocs ; extra == "docs"
Requires-Dist: mkdocs-material ; extra == "docs"
Requires-Dist: pydantic
Requires-Dist: requests
Requires-Dist: typer
Requires-Dist: typing-extensions
Project-URL: Documentation, https://nf1s.github.io/covid/
Project-URL: Repository, https://github.com/nf1s/covid
